Exercise.srcs/sources_1/new/Memory.sv
`timescale 1ns / 1ps
//////////////////////////////////////////////////////////////////////////////////
// Company: 
// Engineer: 
// 
// Create Date: 2025/12/09 14:15:11
// Design Name: 
// Module Name: r_memory
// Project Name: 
// Target Devices: 
// Tool Versions: 
// Description: 
// 
// Dependencies: 
// 
// Revision:
// Revision 0.01 - File Created
// Additional Comments:
// 
//////////////////////////////////////////////////////////////////////////////////


module Memory(
    input logic clk,
    input logic rst,
    input logic rd_en0, rd_en1, rd_en2,
    input logic [9:0] rd_add0, rd_add1, rd_add2,
    input logic wr_en,
    input logic [9:0] wr_add,
    input logic [15:0] wr_data,
    output logic [15:0] rd_data0, rd_data1, rd_data2
    );

    /*
    读写时地址均以上升沿后的地址为准, 使能信号看上升沿时是否有使能信号"""
    */
    //==r_memory==
    // 32*32 16bits
    reg [15:0] r_memory [1023:0];
    //==assign==
    //==always==
    //--rd_data--
    always_ff @(posedge clk or posedge rst) begin
        if(rst == 1) begin
            rd_data0 <= 0;
            rd_data1 <= 0;
            rd_data2 <= 0;
        end
        else begin
            if (rd_en0 == 1) begin
                rd_data0 <= r_memory[rd_add0];
            end
            else begin
                rd_data0 <= 0;
            end

            if(rd_en1 == 1) begin
                rd_data1 <= r_memory[rd_add1];
            end
            else begin
                rd_data1 <= 0;
            end

            if(rd_en2 == 1) begin
                rd_data2 <= r_memory[rd_add2];
            end
            else begin
                rd_data2 <= 0;
            end
            
        end
    end

    //--wr_data--
    always_ff @( posedge clk or posedge rst ) begin
        if(rst == 1) begin
            foreach(r_memory[i,j]) begin
                r_memory[i][j] <= 0;
            end
        end
        else begin
            if(wr_en == 1) begin
                r_memory[wr_add] <= wr_data;
            end
            else begin
                r_memory[wr_add] <= r_memory[wr_add];
            end
        end
    end
endmodule

Exercise.srcs/sim_1/new/tb_Memory.sv
`timescale 1ns / 1ps
//////////////////////////////////////////////////////////////////////////////////
// Company: 
// Engineer: 
// 
// Create Date: 2025/12/09 15:02:51
// Design Name: 
// Module Name: tb_Memory
// Project Name: 
// Target Devices: 
// Tool Versions: 
// Description: 
// 
// Dependencies: 
// 
// Revision:
// Revision 0.01 - File Created
// Additional Comments:
// 
//////////////////////////////////////////////////////////////////////////////////


`timescale 1ns/1ps

module tb_Memory;

// 时钟参数
parameter CLK_PERIOD = 10;  // 100MHz时钟

// 接口信号
logic clk;
logic rst;
logic rd_en0, rd_en1, rd_en2;
logic [9:0] rd_add0, rd_add1, rd_add2;
logic wr_en;
logic [9:0] wr_add;
logic [15:0] wr_data;
logic [15:0] rd_data0, rd_data1, rd_data2;

// 实例化被测试模块
Memory dut (
    .clk(clk),
    .rst(rst),
    .rd_en0(rd_en0),
    .rd_en1(rd_en1),
    .rd_en2(rd_en2),
    .rd_add0(rd_add0),
    .rd_add1(rd_add1),
    .rd_add2(rd_add2),
    .wr_en(wr_en),
    .wr_add(wr_add),
    .wr_data(wr_data),
    .rd_data0(rd_data0),
    .rd_data1(rd_data1),
    .rd_data2(rd_data2)
);

// 时钟生成
initial begin
    clk = 0;
    forever #(CLK_PERIOD/2) clk = ~clk;
end

// 测试控制
integer error_count = 0;
integer test_count = 0;
task automatic wr_matrix(
    input int H = 16,
    input int W = 16,
    input int base_add = 0
);
    int matrix[][];
    
    matrix = new[H];
    for (int i = 0; i < H; i++) begin
        matrix[i] = new[W];
    end
    
    for (int i = 0; i < H; i++) begin
        for (int j = 0; j < W; j++) begin
            @(posedge clk);
            wr_en = 1;
            matrix[i][j] = $urandom_range(20, 0);
            wr_add = base_add + i * W + j;
            wr_data = matrix[i][j];
            $write("%d ",matrix[i][j]);
        end
        $write("\n");
    end
    @(posedge clk);
    wr_en = 0;
endtask
task automatic rd_matrix(
    input int H = 16,
    input int W = 16,
    input int base_add = 0
);
    for (int i = 0; i < H; i++) begin
        for (int j = 0; j < W; j++) begin
            @(posedge clk);
            rd_en0 = 1;
            rd_add0 = base_add + i * W + j;
        end
    end
    @(posedge clk);
    rd_en0 = 0;
endtask 
initial begin
    $display("==========================================");
    $display("Memory Module Testbench");
    $display("==========================================");
    
    // 初始化信号
    rst = 0;
    rd_en0 = 0;
    rd_en1 = 0;
    rd_en2 = 0;
    rd_add0 = 0;
    rd_add1 = 0;
    rd_add2 = 0;
    wr_en = 0;
    wr_add = 0;
    wr_data = 0;
    
    //矩阵输入
    wr_matrix(14,16,0);
    @(posedge clk);
    rd_matrix(14,16,0);
    $finish;
end

// 波形记录
initial begin
    $dumpfile("tb_memory.vcd");
    $dumpvars(0, tb_Memory);
end

// 超时保护
initial begin
    #1000000;  // 1ms超时
    $display("ERROR: Simulation timeout!");
    $finish;
end

endmodule

Exercise.sim/sim_1/behav/xsim/tb_memory.vcd
$date
   Wed Dec 10 16:52:14 2025
$end
$version
  2020.1
$end
$timescale
  1ps
$end
$scope module tb_Memory $end
$var reg 1 ! clk $end
$var reg 1 " rst $end
$var reg 1 # rd_en0 $end
$var reg 1 $ rd_en1 $end
$var reg 1 % rd_en2 $end
$var reg 10 & rd_add0 [9:0] $end
$var reg 10 ' rd_add1 [9:0] $end
$var reg 10 ( rd_add2 [9:0] $end
$var reg 1 ) wr_en $end
$var reg 10 * wr_add [9:0] $end
$var reg 16 + wr_data [15:0] $end
$var reg 16 , rd_data0 [15:0] $end
$var reg 16 - rd_data1 [15:0] $end
$var reg 16 . rd_data2 [15:0] $end
$var integer 32 / error_count $end
$var integer 32 0 test_count $end
$var parameter 32 1 CLK_PERIOD [31:0] $end
$scope module dut $end
$var wire 1 2 clk $end
$var wire 1 3 rst $end
$var wire 1 4 rd_en0 $end
$var wire 1 5 rd_en1 $end
$var wire 1 6 rd_en2 $end
$var wire 10 7 rd_add0 [9:0] $end
$var wire 10 8 rd_add1 [9:0] $end
$var wire 10 9 rd_add2 [9:0] $end
$var wire 1 : wr_en $end
$var wire 10 ; wr_add [9:0] $end
$var wire 16 < wr_data [15:0] $end
$var reg 16 , rd_data0 [15:0] $end
$var reg 16 - rd_data1 [15:0] $end
$var reg 16 . rd_data2 [15:0] $end
$scope begin Block77_2 $end
$var reg 32 = i $end
$scope begin Block77_3 $end
$var reg 32 > j $end
$upscope $end
$upscope $end
$upscope $end
$scope task wr_matrix $end
$var reg 32 ? H $end
$var reg 32 @ W $end
$var reg 32 A base_add $end
$var reg 32 B matrix $end
$scope begin Block75_5 $end
$var reg 32 C i $end
$upscope $end
$scope begin Block79_6 $end
$var reg 32 C i $end
$scope begin Block80_7 $end
$var reg 32 C j $end
$upscope $end
$upscope $end
$upscope $end
$scope task rd_matrix $end
$var reg 32 ? H $end
$var reg 32 @ W $end
$var reg 32 A base_add $end
$scope begin Block98_8 $end
$var reg 32 C i $end
$scope begin Block99_9 $end
$var reg 32 C j $end
$upscope $end
$upscope $end
$upscope $end
$upscope $end
$enddefinitions $end
#0
$dumpvars
0!
0"
0#
0$
0%
b0 &
b0 '
b0 (
0)
b0 *
b0 +
bx ,
bx -
bx .
b0 /
b0 0
b1010 1
02
03
04
05
06
b0 7
b0 8
b0 9
0:
b0 ;
b0 <
b0 =
b0 >
b0 ?
b0 @
b0 A
b0 B
b0 C
$end
#5000
1!
1)
b0 *
b10000 +
b0 ,
b0 -
b0 .
12
1:
b10000 <
#10000
0!
02
#15000
1!
b1 *
b10010 +
12
b1 ;
b10010 <
#20000
0!
02
#25000
1!
b10 *
b10 +
12
b10 ;
b10 <
#30000
0!
02
#35000
1!
b11 *
b111 +
12
b11 ;
b111 <
#40000
0!
02
#45000
1!
b100 *
b10001 +
12
b100 ;
b10001 <
#50000
0!
02
#55000
1!
b101 *
b1111 +
12
b101 ;
b1111 <
#60000
0!
02
#65000
1!
b110 *
b101 +
12
b110 ;
b101 <
#70000
0!
02
#75000
1!
b111 *
b1000 +
12
b111 ;
b1000 <
#80000
0!
02
#85000
1!
b1000 *
b1000 +
12
b1000 ;
#90000
0!
02
#95000
1!
b1001 *
b110 +
12
b1001 ;
b110 <
#100000
0!
02
#105000
1!
b1010 *
b1011 +
12
b1010 ;
b1011 <
#110000
0!
02
#115000
1!
b1011 *
b0 +
12
b1011 ;
b0 <
#120000
0!
02
#125000
1!
b1100 *
b10001 +
12
b1100 ;
b10001 <
#130000
0!
02
#135000
1!
b1101 *
b1101 +
12
b1101 ;
b1101 <
#140000
0!
02
#145000
1!
b1110 *
b100 +
12
b1110 ;
b100 <
#150000
0!
02
#155000
1!
b1111 *
b10100 +
12
b1111 ;
b10100 <
#160000
0!
02
#165000
1!
b10000 *
b1111 +
12
b10000 ;
b1111 <
#170000
0!
02
#175000
1!
b10001 *
b1100 +
12
b10001 ;
b1100 <
#180000
0!
02
#185000
1!
b10010 *
b10100 +
12
b10010 ;
b10100 <
#190000
0!
02
#195000
1!
b10011 *
b1011 +
12
b10011 ;
b1011 <
#200000
0!
02
#205000
1!
b10100 *
b110 +
12
b10100 ;
b110 <
#210000
0!
02
#215000
1!
b10101 *
b10 +
12
b10101 ;
b10 <
#220000
0!
02
#225000
1!
b10110 *
b1010 +
12
b10110 ;
b1010 <
#230000
0!
02
#235000
1!
b10111 *
b0 +
12
b10111 ;
b0 <
#240000
0!
02
#245000
1!
b11000 *
b1110 +
12
b11000 ;
b1110 <
#250000
0!
02
#255000
1!
b11001 *
b100 +
12
b11001 ;
b100 <
#260000
0!
02
#265000
1!
b11010 *
b111 +
12
b11010 ;
b111 <
#270000
0!
02
#275000
1!
b11011 *
b1110 +
12
b11011 ;
b1110 <
#280000
0!
02
#285000
1!
b11100 *
b110 +
12
b11100 ;
b110 <
#290000
0!
02
#295000
1!
b11101 *
b1100 +
12
b11101 ;
b1100 <
#300000
0!
02
#305000
1!
b11110 *
b1010 +
12
b11110 ;
b1010 <
#310000
0!
02
#315000
1!
b11111 *
b10000 +
12
b11111 ;
b10000 <
#320000
0!
02
#325000
1!
b100000 *
b10010 +
12
b100000 ;
b10010 <
#330000
0!
02
#335000
1!
b100001 *
b10001 +
12
b100001 ;
b10001 <
#340000
0!
02
#345000
1!
b100010 *
b1001 +
12
b100010 ;
b1001 <
#350000
0!
02
#355000
1!
b100011 *
b10100 +
12
b100011 ;
b10100 <
#360000
0!
02
#365000
1!
b100100 *
b1000 +
12
b100100 ;
b1000 <
#370000
0!
02
#375000
1!
b100101 *
b1111 +
12
b100101 ;
b1111 <
#380000
0!
02
#385000
1!
b100110 *
b1001 +
12
b100110 ;
b1001 <
#390000
0!
02
#395000
1!
b100111 *
b1 +
12
b100111 ;
b1 <
#400000
0!
02
#405000
1!
b101000 *
b1011 +
12
b101000 ;
b1011 <
#410000
0!
02
#415000
1!
b101001 *
b1110 +
12
b101001 ;
b1110 <
#420000
0!
02
#425000
1!
b101010 *
b10001 +
12
b101010 ;
b10001 <
#430000
0!
02
#435000
1!
b101011 *
b1110 +
12
b101011 ;
b1110 <
#440000
0!
02
#445000
1!
b101100 *
b1000 +
12
b101100 ;
b1000 <
#450000
0!
02
#455000
1!
b101101 *
b101 +
12
b101101 ;
b101 <
#460000
0!
02
#465000
1!
b101110 *
b1101 +
12
b101110 ;
b1101 <
#470000
0!
02
#475000
1!
b101111 *
b10011 +
12
b101111 ;
b10011 <
#480000
0!
02
#485000
1!
b110000 *
b10011 +
12
b110000 ;
#490000
0!
02
#495000
1!
b110001 *
b110 +
12
b110001 ;
b110 <
#500000
0!
02
#505000
1!
b110010 *
b1010 +
12
b110010 ;
b1010 <
#510000
0!
02
#515000
1!
b110011 *
b110 +
12
b110011 ;
b110 <
#520000
0!
02
#525000
1!
b110100 *
b1011 +
12
b110100 ;
b1011 <
#530000
0!
02
#535000
1!
b110101 *
b10100 +
12
b110101 ;
b10100 <
#540000
0!
02
#545000
1!
b110110 *
b10100 +
12
b110110 ;
#550000
0!
02
#555000
1!
b110111 *
b1000 +
12
b110111 ;
b1000 <
#560000
0!
02
#565000
1!
b111000 *
b101 +
12
b111000 ;
b101 <
#570000
0!
02
#575000
1!
b111001 *
b1001 +
12
b111001 ;
b1001 <
#580000
0!
02
#585000
1!
b111010 *
b1010 +
12
b111010 ;
b1010 <
#590000
0!
02
#595000
1!
b111011 *
b10000 +
12
b111011 ;
b10000 <
#600000
0!
02
#605000
1!
b111100 *
b1000 +
12
b111100 ;
b1000 <
#610000
0!
02
#615000
1!
b111101 *
b1001 +
12
b111101 ;
b1001 <
#620000
0!
02
#625000
1!
b111110 *
b10100 +
12
b111110 ;
b10100 <
#630000
0!
02
#635000
1!
b111111 *
b1011 +
12
b111111 ;
b1011 <
#640000
0!
02
#645000
1!
b1000000 *
b1111 +
12
b1000000 ;
b1111 <
#650000
0!
02
#655000
1!
b1000001 *
b100 +
12
b1000001 ;
b100 <
#660000
0!
02
#665000
1!
b1000010 *
b101 +
12
b1000010 ;
b101 <
#670000
0!
02
#675000
1!
b1000011 *
b10011 +
12
b1000011 ;
b10011 <
#680000
0!
02
#685000
1!
b1000100 *
b1011 +
12
b1000100 ;
b1011 <
#690000
0!
02
#695000
1!
b1000101 *
b0 +
12
b1000101 ;
b0 <
#700000
0!
02
#705000
1!
b1000110 *
b110 +
12
b1000110 ;
b110 <
#710000
0!
02
#715000
1!
b1000111 *
b11 +
12
b1000111 ;
b11 <
#720000
0!
02
#725000
1!
b1001000 *
b100 +
12
b1001000 ;
b100 <
#730000
0!
02
#735000
1!
b1001001 *
b111 +
12
b1001001 ;
b111 <
#740000
0!
02
#745000
1!
b1001010 *
b10001 +
12
b1001010 ;
b10001 <
#750000
0!
02
#755000
1!
b1001011 *
b1010 +
12
b1001011 ;
b1010 <
#760000
0!
02
#765000
1!
b1001100 *
b111 +
12
b1001100 ;
b111 <
#770000
0!
02
#775000
1!
b1001101 *
b10 +
12
b1001101 ;
b10 <
#780000
0!
02
#785000
1!
b1001110 *
b1101 +
12
b1001110 ;
b1101 <
#790000
0!
02
#795000
1!
b1001111 *
b110 +
12
b1001111 ;
b110 <
#800000
0!
02
#805000
1!
b1010000 *
b1001 +
12
b1010000 ;
b1001 <
#810000
0!
02
#815000
1!
b1010001 *
b1001 +
12
b1010001 ;
#820000
0!
02
#825000
1!
b1010010 *
b10000 +
12
b1010010 ;
b10000 <
#830000
0!
02
#835000
1!
b1010011 *
b10000 +
12
b1010011 ;
#840000
0!
02
#845000
1!
b1010100 *
b1001 +
12
b1010100 ;
b1001 <
#850000
0!
02
#855000
1!
b1010101 *
b110 +
12
b1010101 ;
b110 <
#860000
0!
02
#865000
1!
b1010110 *
b10100 +
12
b1010110 ;
b10100 <
#870000
0!
02
#875000
1!
b1010111 *
b10010 +
12
b1010111 ;
b10010 <
#880000
0!
02
#885000
1!
b1011000 *
b1010 +
12
b1011000 ;
b1010 <
#890000
0!
02
#895000
1!
b1011001 *
b1111 +
12
b1011001 ;
b1111 <
#900000
0!
02
#905000
1!
b1011010 *
b1010 +
12
b1011010 ;
b1010 <
#910000
0!
02
#915000
1!
b1011011 *
b10011 +
12
b1011011 ;
b10011 <
#920000
0!
02
#925000
1!
b1011100 *
b10100 +
12
b1011100 ;
b10100 <
#930000
0!
02
#935000
1!
b1011101 *
b111 +
12
b1011101 ;
b111 <
#940000
0!
02
#945000
1!
b1011110 *
b1011 +
12
b1011110 ;
b1011 <
#950000
0!
02
#955000
1!
b1011111 *
b101 +
12
b1011111 ;
b101 <
#960000
0!
02
#965000
1!
b1100000 *
b10001 +
12
b1100000 ;
b10001 <
#970000
0!
02
#975000
1!
b1100001 *
b0 +
12
b1100001 ;
b0 <
#980000
0!
02
#985000
1!
b1100010 *
b11 +
12
b1100010 ;
b11 <
#990000
0!
02
#995000
1!
b1100011 *
b1100 +
12
b1100011 ;
b1100 <
#1000000
0!
02
#1005000
1!
b1100100 *
b11 +
12
b1100100 ;
b11 <
#1010000
0!
02
#1015000
1!
b1100101 *
b1100 +
12
b1100101 ;
b1100 <
#1020000
0!
02
#1025000
1!
b1100110 *
b10001 +
12
b1100110 ;
b10001 <
#1030000
0!
02
#1035000
1!
b1100111 *
b10010 +
12
b1100111 ;
b10010 <
#1040000
0!
02
#1045000
1!
b1101000 *
b1000 +
12
b1101000 ;
b1000 <
#1050000
0!
02
#1055000
1!
b1101001 *
b10010 +
12
b1101001 ;
b10010 <
#1060000
0!
02
#1065000
1!
b1101010 *
b1001 +
12
b1101010 ;
b1001 <
#1070000
0!
02
#1075000
1!
b1101011 *
b1010 +
12
b1101011 ;
b1010 <
#1080000
0!
02
#1085000
1!
b1101100 *
b110 +
12
b1101100 ;
b110 <
#1090000
0!
02
#1095000
1!
b1101101 *
b101 +
12
b1101101 ;
b101 <
#1100000
0!
02
#1105000
1!
b1101110 *
b101 +
12
b1101110 ;
#1110000
0!
02
#1115000
1!
b1101111 *
b1110 +
12
b1101111 ;
b1110 <
#1120000
0!
02
#1125000
1!
b1110000 *
b10010 +
12
b1110000 ;
b10010 <
#1130000
0!
02
#1135000
1!
b1110001 *
b1001 +
12
b1110001 ;
b1001 <
#1140000
0!
02
#1145000
1!
b1110010 *
b10100 +
12
b1110010 ;
b10100 <
#1150000
0!
02
#1155000
1!
b1110011 *
b11 +
12
b1110011 ;
b11 <
#1160000
0!
02
#1165000
1!
b1110100 *
b1110 +
12
b1110100 ;
b1110 <
#1170000
0!
02
#1175000
1!
b1110101 *
b11 +
12
b1110101 ;
b11 <
#1180000
0!
02
#1185000
1!
b1110110 *
b10001 +
12
b1110110 ;
b10001 <
#1190000
0!
02
#1195000
1!
b1110111 *
b1011 +
12
b1110111 ;
b1011 <
#1200000
0!
02
#1205000
1!
b1111000 *
b1000 +
12
b1111000 ;
b1000 <
#1210000
0!
02
#1215000
1!
b1111001 *
b1011 +
12
b1111001 ;
b1011 <
#1220000
0!
02
#1225000
1!
b1111010 *
b1100 +
12
b1111010 ;
b1100 <
#1230000
0!
02
#1235000
1!
b1111011 *
b1 +
12
b1111011 ;
b1 <
#1240000
0!
02
#1245000
1!
b1111100 *
b1010 +
12
b1111100 ;
b1010 <
#1250000
0!
02
#1255000
1!
b1111101 *
b11 +
12
b1111101 ;
b11 <
#1260000
0!
02
#1265000
1!
b1111110 *
b1001 +
12
b1111110 ;
b1001 <
#1270000
0!
02
#1275000
1!
b1111111 *
b10010 +
12
b1111111 ;
b10010 <
#1280000
0!
02
#1285000
1!
b10000000 *
b1110 +
12
b10000000 ;
b1110 <
#1290000
0!
02
#1295000
1!
b10000001 *
b10001 +
12
b10000001 ;
b10001 <
#1300000
0!
02
#1305000
1!
b10000010 *
b10011 +
12
b10000010 ;
b10011 <
#1310000
0!
02
#1315000
1!
b10000011 *
b101 +
12
b10000011 ;
b101 <
#1320000
0!
02
#1325000
1!
b10000100 *
b10100 +
12
b10000100 ;
b10100 <
#1330000
0!
02
#1335000
1!
b10000101 *
b11 +
12
b10000101 ;
b11 <
#1340000
0!
02
#1345000
1!
b10000110 *
b10 +
12
b10000110 ;
b10 <
#1350000
0!
02
#1355000
1!
b10000111 *
b1101 +
12
b10000111 ;
b1101 <
#1360000
0!
02
#1365000
1!
b10001000 *
b10011 +
12
b10001000 ;
b10011 <
#1370000
0!
02
#1375000
1!
b10001001 *
b10001 +
12
b10001001 ;
b10001 <
#1380000
0!
02
#1385000
1!
b10001010 *
b1110 +
12
b10001010 ;
b1110 <
#1390000
0!
02
#1395000
1!
b10001011 *
b1110 +
12
b10001011 ;
#1400000
0!
02
#1405000
1!
b10001100 *
b1111 +
12
b10001100 ;
b1111 <
#1410000
0!
02
#1415000
1!
b10001101 *
b1100 +
12
b10001101 ;
b1100 <
#1420000
0!
02
#1425000
1!
b10001110 *
b101 +
12
b10001110 ;
b101 <
#1430000
0!
02
#1435000
1!
b10001111 *
b1001 +
12
b10001111 ;
b1001 <
#1440000
0!
02
#1445000
1!
b10010000 *
b111 +
12
b10010000 ;
b111 <
#1450000
0!
02
#1455000
1!
b10010001 *
b1111 +
12
b10010001 ;
b1111 <
#1460000
0!
02
#1465000
1!
b10010010 *
b10 +
12
b10010010 ;
b10 <
#1470000
0!
02
#1475000
1!
b10010011 *
b10010 +
12
b10010011 ;
b10010 <
#1480000
0!
02
#1485000
1!
b10010100 *
b101 +
12
b10010100 ;
b101 <
#1490000
0!
02
#1495000
1!
b10010101 *
b101 +
12
b10010101 ;
#1500000
0!
02
#1505000
1!
b10010110 *
b110 +
12
b10010110 ;
b110 <
#1510000
0!
02
#1515000
1!
b10010111 *
b1000 +
12
b10010111 ;
b1000 <
#1520000
0!
02
#1525000
1!
b10011000 *
b1111 +
12
b10011000 ;
b1111 <
#1530000
0!
02
#1535000
1!
b10011001 *
b1000 +
12
b10011001 ;
b1000 <
#1540000
0!
02
#1545000
1!
b10011010 *
b101 +
12
b10011010 ;
b101 <
#1550000
0!
02
#1555000
1!
b10011011 *
b10100 +
12
b10011011 ;
b10100 <
#1560000
0!
02
#1565000
1!
b10011100 *
b1010 +
12
b10011100 ;
b1010 <
#1570000
0!
02
#1575000
1!
b10011101 *
b111 +
12
b10011101 ;
b111 <
#1580000
0!
02
#1585000
1!
b10011110 *
b11 +
12
b10011110 ;
b11 <
#1590000
0!
02
#1595000
1!
b10011111 *
b100 +
12
b10011111 ;
b100 <
#1600000
0!
02
#1605000
1!
b10100000 *
b1111 +
12
b10100000 ;
b1111 <
#1610000
0!
02
#1615000
1!
b10100001 *
b10 +
12
b10100001 ;
b10 <
#1620000
0!
02
#1625000
1!
b10100010 *
b10100 +
12
b10100010 ;
b10100 <
#1630000
0!
02
#1635000
1!
b10100011 *
b0 +
12
b10100011 ;
b0 <
#1640000
0!
02
#1645000
1!
b10100100 *
b1011 +
12
b10100100 ;
b1011 <
#1650000
0!
02
#1655000
1!
b10100101 *
b10001 +
12
b10100101 ;
b10001 <
#1660000
0!
02
#1665000
1!
b10100110 *
b0 +
12
b10100110 ;
b0 <
#1670000
0!
02
#1675000
1!
b10100111 *
b1 +
12
b10100111 ;
b1 <
#1680000
0!
02
#1685000
1!
b10101000 *
b0 +
12
b10101000 ;
b0 <
#1690000
0!
02
#1695000
1!
b10101001 *
b10000 +
12
b10101001 ;
b10000 <
#1700000
0!
02
#1705000
1!
b10101010 *
b10001 +
12
b10101010 ;
b10001 <
#1710000
0!
02
#1715000
1!
b10101011 *
b111 +
12
b10101011 ;
b111 <
#1720000
0!
02
#1725000
1!
b10101100 *
b1100 +
12
b10101100 ;
b1100 <
#1730000
0!
02
#1735000
1!
b10101101 *
b10001 +
12
b10101101 ;
b10001 <
#1740000
0!
02
#1745000
1!
b10101110 *
b100 +
12
b10101110 ;
b100 <
#1750000
0!
02
#1755000
1!
b10101111 *
b1000 +
12
b10101111 ;
b1000 <
#1760000
0!
02
#1765000
1!
b10110000 *
b1011 +
12
b10110000 ;
b1011 <
#1770000
0!
02
#1775000
1!
b10110001 *
b0 +
12
b10110001 ;
b0 <
#1780000
0!
02
#1785000
1!
b10110010 *
b1101 +
12
b10110010 ;
b1101 <
#1790000
0!
02
#1795000
1!
b10110011 *
b10011 +
12
b10110011 ;
b10011 <
#1800000
0!
02
#1805000
1!
b10110100 *
b1100 +
12
b10110100 ;
b1100 <
#1810000
0!
02
#1815000
1!
b10110101 *
b1100 +
12
b10110101 ;
#1820000
0!
02
#1825000
1!
b10110110 *
b101 +
12
b10110110 ;
b101 <
#1830000
0!
02
#1835000
1!
b10110111 *
b10011 +
12
b10110111 ;
b10011 <
#1840000
0!
02
#1845000
1!
b10111000 *
b1010 +
12
b10111000 ;
b1010 <
#1850000
0!
02
#1855000
1!
b10111001 *
b1110 +
12
b10111001 ;
b1110 <
#1860000
0!
02
#1865000
1!
b10111010 *
b10001 +
12
b10111010 ;
b10001 <
#1870000
0!
02
#1875000
1!
b10111011 *
b1 +
12
b10111011 ;
b1 <
#1880000
0!
02
#1885000
1!
b10111100 *
b11 +
12
b10111100 ;
b11 <
#1890000
0!
02
#1895000
1!
b10111101 *
b10010 +
12
b10111101 ;
b10010 <
#1900000
0!
02
#1905000
1!
b10111110 *
b10010 +
12
b10111110 ;
#1910000
0!
02
#1915000
1!
b10111111 *
b1010 +
12
b10111111 ;
b1010 <
#1920000
0!
02
#1925000
1!
b11000000 *
b110 +
12
b11000000 ;
b110 <
#1930000
0!
02
#1935000
1!
b11000001 *
b1101 +
12
b11000001 ;
b1101 <
#1940000
0!
02
#1945000
1!
b11000010 *
b1011 +
12
b11000010 ;
b1011 <
#1950000
0!
02
#1955000
1!
b11000011 *
b1001 +
12
b11000011 ;
b1001 <
#1960000
0!
02
#1965000
1!
b11000100 *
b110 +
12
b11000100 ;
b110 <
#1970000
0!
02
#1975000
1!
b11000101 *
b111 +
12
b11000101 ;
b111 <
#1980000
0!
02
#1985000
1!
b11000110 *
b10011 +
12
b11000110 ;
b10011 <
#1990000
0!
02
#1995000
1!
b11000111 *
b1010 +
12
b11000111 ;
b1010 <
#2000000
0!
02
#2005000
1!
b11001000 *
b10000 +
12
b11001000 ;
b10000 <
#2010000
0!
02
#2015000
1!
b11001001 *
b100 +
12
b11001001 ;
b100 <
#2020000
0!
02
#2025000
1!
b11001010 *
b10000 +
12
b11001010 ;
b10000 <
#2030000
0!
02
#2035000
1!
b11001011 *
b10010 +
12
b11001011 ;
b10010 <
#2040000
0!
02
#2045000
1!
b11001100 *
b1011 +
12
b11001100 ;
b1011 <
#2050000
0!
02
#2055000
1!
b11001101 *
b1110 +
12
b11001101 ;
b1110 <
#2060000
0!
02
#2065000
1!
b11001110 *
b100 +
12
b11001110 ;
b100 <
#2070000
0!
02
#2075000
1!
b11001111 *
b10 +
12
b11001111 ;
b10 <
#2080000
0!
02
#2085000
1!
b11010000 *
b10000 +
12
b11010000 ;
b10000 <
#2090000
0!
02
#2095000
1!
b11010001 *
b1 +
12
b11010001 ;
b1 <
#2100000
0!
02
#2105000
1!
b11010010 *
b10010 +
12
b11010010 ;
b10010 <
#2110000
0!
02
#2115000
1!
b11010011 *
b10 +
12
b11010011 ;
b10 <
#2120000
0!
02
#2125000
1!
b11010100 *
b1011 +
12
b11010100 ;
b1011 <
#2130000
0!
02
#2135000
1!
b11010101 *
b10100 +
12
b11010101 ;
b10100 <
#2140000
0!
02
#2145000
1!
b11010110 *
b10 +
12
b11010110 ;
b10 <
#2150000
0!
02
#2155000
1!
b11010111 *
b101 +
12
b11010111 ;
b101 <
#2160000
0!
02
#2165000
1!
b11011000 *
b10011 +
12
b11011000 ;
b10011 <
#2170000
0!
02
#2175000
1!
b11011001 *
b1111 +
12
b11011001 ;
b1111 <
#2180000
0!
02
#2185000
1!
b11011010 *
b101 +
12
b11011010 ;
b101 <
#2190000
0!
02
#2195000
1!
b11011011 *
b110 +
12
b11011011 ;
b110 <
#2200000
0!
02
#2205000
1!
b11011100 *
b1110 +
12
b11011100 ;
b1110 <
#2210000
0!
02
#2215000
1!
b11011101 *
b10 +
12
b11011101 ;
b10 <
#2220000
0!
02
#2225000
1!
b11011110 *
b101 +
12
b11011110 ;
b101 <
#2230000
0!
02
#2235000
1!
b11011111 *
b1001 +
12
b11011111 ;
b1001 <
#2240000
0!
02
#2245000
1!
0)
12
0:
#2250000
0!
02
#2255000
1!
12
#2260000
0!
02
#2265000
1!
1#
b0 &
b10000 ,
12
14
#2270000
0!
02
#2275000
1!
b1 &
b10010 ,
12
b1 7
#2280000
0!
02
#2285000
1!
b10 &
b10 ,
12
b10 7
#2290000
0!
02
#2295000
1!
b11 &
b111 ,
12
b11 7
#2300000
0!
02
#2305000
1!
b100 &
b10001 ,
12
b100 7
#2310000
0!
02
#2315000
1!
b101 &
b1111 ,
12
b101 7
#2320000
0!
02
#2325000
1!
b110 &
b101 ,
12
b110 7
#2330000
0!
02
#2335000
1!
b111 &
b1000 ,
12
b111 7
#2340000
0!
02
#2345000
1!
b1000 &
12
b1000 7
#2350000
0!
02
#2355000
1!
b1001 &
b110 ,
12
b1001 7
#2360000
0!
02
#2365000
1!
b1010 &
b1011 ,
12
b1010 7
#2370000
0!
02
#2375000
1!
b1011 &
b0 ,
12
b1011 7
#2380000
0!
02
#2385000
1!
b1100 &
b10001 ,
12
b1100 7
#2390000
0!
02
#2395000
1!
b1101 &
b1101 ,
12
b1101 7
#2400000
0!
02
#2405000
1!
b1110 &
b100 ,
12
b1110 7
#2410000
0!
02
#2415000
1!
b1111 &
b10100 ,
12
b1111 7
#2420000
0!
02
#2425000
1!
b10000 &
b1111 ,
12
b10000 7
#2430000
0!
02
#2435000
1!
b10001 &
b1100 ,
12
b10001 7
#2440000
0!
02
#2445000
1!
b10010 &
b10100 ,
12
b10010 7
#2450000
0!
02
#2455000
1!
b10011 &
b1011 ,
12
b10011 7
#2460000
0!
02
#2465000
1!
b10100 &
b110 ,
12
b10100 7
#2470000
0!
02
#2475000
1!
b10101 &
b10 ,
12
b10101 7
#2480000
0!
02
#2485000
1!
b10110 &
b1010 ,
12
b10110 7
#2490000
0!
02
#2495000
1!
b10111 &
b0 ,
12
b10111 7
#2500000
0!
02
#2505000
1!
b11000 &
b1110 ,
12
b11000 7
#2510000
0!
02
#2515000
1!
b11001 &
b100 ,
12
b11001 7
#2520000
0!
02
#2525000
1!
b11010 &
b111 ,
12
b11010 7
#2530000
0!
02
#2535000
1!
b11011 &
b1110 ,
12
b11011 7
#2540000
0!
02
#2545000
1!
b11100 &
b110 ,
12
b11100 7
#2550000
0!
02
#2555000
1!
b11101 &
b1100 ,
12
b11101 7
#2560000
0!
02
#2565000
1!
b11110 &
b1010 ,
12
b11110 7
#2570000
0!
02
#2575000
1!
b11111 &
b10000 ,
12
b11111 7
#2580000
0!
02
#2585000
1!
b100000 &
b10010 ,
12
b100000 7
#2590000
0!
02
#2595000
1!
b100001 &
b10001 ,
12
b100001 7
#2600000
0!
02
#2605000
1!
b100010 &
b1001 ,
12
b100010 7
#2610000
0!
02
#2615000
1!
b100011 &
b10100 ,
12
b100011 7
